{
    "id": "kubejs:lesser_blood_ring",
    "modifiers": [
      {
        "type": "append",
        "attribute": "alembic:true_damage.resistance",
        "value": 1,
        "operation": "ADDITION",
        "uuid": "c50a32b5-5490-45fa-bf10-a98c8f929ca6"
      },
      {
        "type": "append",
        "attribute": "irons_spellbooks:blood_spell_power",
        "value": 0.05,
        "operation": "MULTIPLY_TOTAL",
        "uuid": "1b123927-3123-42e8-ae76-a103964a354a"
      }
    ],
    "equipment_slot": "ring"
  }